{
    "domain": "zeotap.com",
    "owner": {
        "name": "Zeotap GmbH",
        "displayName": "Zeotap"
    },
    "source": [
        "DuckDuckGo-GB"
    ],
    "prevalence": 0.00111,
    "sites": 11,
    "subdomains": [
        "spl",
        "mwzeom"
    ],
    "cnames": [],
    "fingerprinting": 1,
    "resources": [
        {
            "rule": "zeotap\\.com\\/",
            "cookies": 0.000604,
            "fingerprinting": 0,
            "subdomains": [
                "spl"
            ],
            "apis": {},
            "sites": 6,
            "prevalence": 0.000604,
            "cnames": [],
            "responseHashes": [],
            "type": "Image",
            "firstPartyCookies": {},
            "firstPartyCookiesSent": {},
            "exampleSites": [
                "draxe.com",
                "en-gb.support.motorola.com",
                "support.lenovo.com",
                "us.norton.com",
                "www.audible.com",
                "www.colgate.com"
            ]
        },
        {
            "rule": "zeotap\\.com\\/mw",
            "cookies": 0.000906,
            "fingerprinting": 0,
            "subdomains": [
                "mwzeom"
            ],
            "apis": {},
            "sites": 9,
            "prevalence": 0.000906,
            "cnames": [],
            "responseHashes": [
                "ac554a4ea8b34bbb80db013e14be195ebc986f82f24e5b18b0ea9032ef561f57"
            ],
            "type": "Image",
            "firstPartyCookies": {},
            "firstPartyCookiesSent": {
                "aam_uuid": 0.00010064412238325282
            },
            "exampleSites": [
                "draxe.com",
                "en-gb.support.motorola.com",
                "support.lenovo.com",
                "us.norton.com",
                "www.audible.com",
                "www.azlyrics.com",
                "www.colgate.com",
                "www.grammar-monster.com",
                "www.hardreset.info"
            ]
        },
        {
            "rule": "zeotap\\.com\\/",
            "cookies": 0.000201,
            "fingerprinting": 0,
            "subdomains": [
                "spl"
            ],
            "apis": {},
            "sites": 2,
            "prevalence": 0.000201,
            "cnames": [],
            "responseHashes": [
                "2d388663e1a05264b272db13b2d75a1b8b2a4922738f99e41e2c62fd56591dad"
            ],
            "type": "Document",
            "firstPartyCookies": {},
            "firstPartyCookiesSent": {},
            "exampleSites": [
                "grammar-monster.com",
                "www.hardreset.info"
            ]
        }
    ],
    "categories": [],
    "performance": {},
    "cookies": 0.00111,
    "topInitiators": [
        {
            "domain": "amazon-adsystem.com",
            "prevalence": 0.47058823529411764
        },
        {
            "domain": "demdex.net",
            "prevalence": 0.23529411764705882
        },
        {
            "domain": "pubmatic.com",
            "prevalence": 0.11764705882352941
        },
        {
            "domain": "adobedtm.com",
            "prevalence": 0.058823529411764705
        },
        {
            "domain": "vlitag.com",
            "prevalence": 0.058823529411764705
        },
        {
            "domain": "adpushup.com",
            "prevalence": 0.058823529411764705
        }
    ],
    "types": {
        "Image": 15,
        "Document": 2
    },
    "nameservers": [
        "kurt.ns.cloudflare.com",
        "tina.ns.cloudflare.com"
    ]
}