{
    "domain": "trinityaudio.ai",
    "owner": {},
    "source": [
        "DuckDuckGo-US"
    ],
    "prevalence": 0.0000205,
    "sites": 3,
    "subdomains": [
        "delivery",
        "cms"
    ],
    "cnames": [],
    "fingerprinting": 0,
    "resources": [
        {
            "rule": "trinityaudio\\.ai\\/v1\\/playlist\\/3hp5nyrp\\/rss",
            "cookies": 0,
            "fingerprinting": 0,
            "subdomains": [
                "delivery"
            ],
            "apis": {},
            "sites": 2,
            "prevalence": 0.0000137,
            "cnames": [],
            "responseHashes": [
                "412242b40958d81b02ca670212b00036fdfe7547a8f2216d9aad09d2ed1ddc4a"
            ],
            "type": "Fetch",
            "firstPartyCookies": {},
            "firstPartyCookiesSent": {},
            "exampleSites": [
                "stripes.com",
                "www.stripes.com"
            ]
        },
        {
            "rule": "trinityaudio\\.ai\\/cms\\/1202\\/image\\/audio\\/2cfea0e0202b89cf15d29f7a98196f091755bf7344b3c36f6e4c2044c205753f\\/rss_banner\\.jpg",
            "cookies": 0,
            "fingerprinting": 0,
            "subdomains": [
                "cms"
            ],
            "apis": {},
            "sites": 2,
            "prevalence": 0.0000137,
            "cnames": [],
            "responseHashes": [
                "f325319924a3dcdbf1e89e4a0876c4975984cf93fa9ed88a63c36381aec2326d"
            ],
            "type": "Image",
            "firstPartyCookies": {},
            "firstPartyCookiesSent": {},
            "exampleSites": [
                "stripes.com",
                "www.stripes.com"
            ]
        }
    ],
    "categories": [],
    "performance": {},
    "cookies": 0,
    "topInitiators": [
        {
            "domain": "trinitymedia.ai",
            "prevalence": 0.6
        },
        {
            "domain": "first party",
            "prevalence": 0.4
        }
    ],
    "types": {
        "Fetch": 2,
        "Image": 2
    },
    "nameservers": [
        "dns1.registrar-servers.com",
        "dns2.registrar-servers.com"
    ]
}