{
    "domain": "transcend-cdn.com",
    "owner": {},
    "source": [
        "DuckDuckGo-CH"
    ],
    "prevalence": 0.00131,
    "sites": 13,
    "subdomains": [],
    "cnames": [],
    "fingerprinting": 2,
    "resources": [
        {
            "rule": "transcend-cdn\\.com\\/cm\\/471944e6-c8d1-4cfe-902c-0ed1695b7053\\/airgap\\.js",
            "cookies": 0.0001,
            "fingerprinting": 2,
            "subdomains": [],
            "apis": {
                "Navigator.prototype.doNotTrack": 2,
                "Navigator.prototype.cookieEnabled": 2,
                "Navigator.prototype.userAgent": 2,
                "window.sessionStorage": 2,
                "window.localStorage": 2,
                "Navigator.prototype.languages": 2,
                "Document.cookie getter": 2,
                "CookieStore.prototype.getAll": 2,
                "Document.cookie setter": 1,
                "Event.prototype.timeStamp": 1
            },
            "sites": 2,
            "prevalence": 0.000201,
            "cnames": [],
            "responseHashes": [
                "5d38c8c99c831fb732f254ff209fcfbbed18b739e4056d94d5a8f5c977c8f5a3"
            ],
            "type": "Script",
            "firstPartyCookies": {
                "utm_source": {
                    "ttl": null,
                    "length": 6,
                    "prevalence": 0.00010048231511254019,
                    "uniqueness": 1
                },
                "utm_medium": {
                    "ttl": null,
                    "length": 8,
                    "prevalence": 0.00010048231511254019,
                    "uniqueness": 1
                },
                "utm_campaign": {
                    "ttl": null,
                    "length": 4,
                    "prevalence": 0.00010048231511254019,
                    "uniqueness": 1
                },
                "utm_content": {
                    "ttl": null,
                    "length": 4,
                    "prevalence": 0.00010048231511254019,
                    "uniqueness": 1
                },
                "utm_term": {
                    "ttl": null,
                    "length": 4,
                    "prevalence": 0.00010048231511254019,
                    "uniqueness": 1
                },
                "_biz_dfsA": {
                    "ttl": -58,
                    "length": 4,
                    "prevalence": 0.00010048231511254019,
                    "uniqueness": 1
                },
                "_biz_kvpA": {
                    "ttl": -58,
                    "length": 4,
                    "prevalence": 0.00010048231511254019,
                    "uniqueness": 1
                },
                "_biz_uid": {
                    "ttl": 31536002,
                    "length": 32,
                    "prevalence": 0.00010048231511254019,
                    "uniqueness": 1
                },
                "_biz_nA": {
                    "ttl": 31536002,
                    "length": 1,
                    "prevalence": 0.00010048231511254019,
                    "uniqueness": 1
                },
                "_biz_pendingA": {
                    "ttl": 31536002,
                    "length": 6,
                    "prevalence": 0.00010048231511254019,
                    "uniqueness": 1
                },
                "_biz_flagsA": {
                    "ttl": 31536003,
                    "length": 79,
                    "prevalence": 0.00010048231511254019,
                    "uniqueness": 1
                },
                "_ga": {
                    "ttl": 63072003,
                    "length": 25,
                    "prevalence": 0.00010048231511254019,
                    "uniqueness": 1
                },
                "_gid": {
                    "ttl": 86403,
                    "length": 27,
                    "prevalence": 0.00010048231511254019,
                    "uniqueness": 1
                },
                "__tld__": {
                    "ttl": null,
                    "length": 1,
                    "prevalence": 0.00010048231511254019,
                    "uniqueness": 1
                },
                "cb%3Atest": {
                    "ttl": 5,
                    "length": 4,
                    "prevalence": 0.00010048231511254019,
                    "uniqueness": 1
                },
                "pfjs%3Acookies": {
                    "ttl": 5,
                    "length": 4,
                    "prevalence": 0.00010048231511254019,
                    "uniqueness": 1
                },
                "cb_user_id": {
                    "ttl": 31536005,
                    "length": 4,
                    "prevalence": 0.00010048231511254019,
                    "uniqueness": 1
                },
                "cb_group_id": {
                    "ttl": 31536005,
                    "length": 4,
                    "prevalence": 0.00010048231511254019,
                    "uniqueness": 1
                },
                "cb_anonymous_id": {
                    "ttl": 31536005,
                    "length": 42,
                    "prevalence": 0.00010048231511254019,
                    "uniqueness": 1
                }
            },
            "firstPartyCookiesSent": {},
            "exampleSites": [
                "anaconda.org",
                "www.anaconda.com"
            ]
        },
        {
            "rule": "transcend-cdn\\.com\\/cm\\/471944e6-c8d1-4cfe-902c-0ed1695b7053\\/ui\\.js",
            "cookies": 0,
            "fingerprinting": 1,
            "subdomains": [],
            "apis": {
                "Navigator.prototype.userAgent": 2,
                "Navigator.prototype.languages": 2
            },
            "sites": 2,
            "prevalence": 0.000201,
            "cnames": [],
            "responseHashes": [
                "746f43b8c8b16559500b7277ba6998fb1114e2fbac6f98a778b49a70f252c5e4"
            ],
            "type": "Script",
            "firstPartyCookies": {},
            "firstPartyCookiesSent": {},
            "exampleSites": [
                "anaconda.org",
                "www.anaconda.com"
            ]
        },
        {
            "rule": "transcend-cdn\\.com\\/cm\\/471944e6-c8d1-4cfe-902c-0ed1695b7053\\/cm\\.css",
            "cookies": 0,
            "fingerprinting": 0,
            "subdomains": [],
            "apis": {},
            "sites": 2,
            "prevalence": 0.000201,
            "cnames": [],
            "responseHashes": [
                "e85c358c6a7e164c3cfa80e657d29f37396142fb5c47f26e9056859448a0c30b"
            ],
            "type": "Stylesheet",
            "firstPartyCookies": {},
            "firstPartyCookiesSent": {},
            "exampleSites": [
                "anaconda.org",
                "www.anaconda.com"
            ]
        },
        {
            "rule": "transcend-cdn\\.com\\/cm\\/471944e6-c8d1-4cfe-902c-0ed1695b7053\\/translations\\/de-DE\\.json",
            "cookies": 0,
            "fingerprinting": 0,
            "subdomains": [],
            "apis": {},
            "sites": 2,
            "prevalence": 0.000201,
            "cnames": [],
            "responseHashes": [
                "3dff8db4b86851475d31fd4c1c717d793ce38e5ce868b014dc4c42f28998a6d7"
            ],
            "type": "Fetch",
            "firstPartyCookies": {},
            "firstPartyCookiesSent": {},
            "exampleSites": [
                "anaconda.org",
                "www.anaconda.com"
            ]
        },
        {
            "rule": "transcend-cdn\\.com\\/cm\\/a36a42ad-3a71-444f-9e8a-b19950129dc6\\/airgap\\.js",
            "cookies": 0,
            "fingerprinting": 2,
            "subdomains": [],
            "apis": {
                "Navigator.prototype.doNotTrack": 2,
                "Navigator.prototype.cookieEnabled": 2,
                "Navigator.prototype.userAgent": 2,
                "window.sessionStorage": 2,
                "window.localStorage": 2,
                "Navigator.prototype.languages": 2,
                "Document.cookie getter": 2,
                "CookieStore.prototype.getAll": 2
            },
            "sites": 2,
            "prevalence": 0.000201,
            "cnames": [],
            "responseHashes": [
                "c851a6fd6fe3edff27754726a1c28862be9dd2b07a0ea25ae3615c889f79773e"
            ],
            "type": "Script",
            "firstPartyCookies": {},
            "firstPartyCookiesSent": {},
            "exampleSites": [
                "notion.so",
                "www.notion.com"
            ]
        },
        {
            "rule": "transcend-cdn\\.com\\/cm\\/a36a42ad-3a71-444f-9e8a-b19950129dc6\\/ui\\.js",
            "cookies": 0,
            "fingerprinting": 1,
            "subdomains": [],
            "apis": {
                "Navigator.prototype.userAgent": 2,
                "Navigator.prototype.languages": 2
            },
            "sites": 2,
            "prevalence": 0.000201,
            "cnames": [],
            "responseHashes": [
                "f088aec73a726e519bd8dfdb5658113aa618ca305373c22a582e8e6760a2dd58"
            ],
            "type": "Script",
            "firstPartyCookies": {},
            "firstPartyCookiesSent": {},
            "exampleSites": [
                "notion.so",
                "www.notion.com"
            ]
        },
        {
            "rule": "transcend-cdn\\.com\\/cm\\/a36a42ad-3a71-444f-9e8a-b19950129dc6\\/translations\\/de-DE\\.json",
            "cookies": 0,
            "fingerprinting": 0,
            "subdomains": [],
            "apis": {},
            "sites": 2,
            "prevalence": 0.000201,
            "cnames": [],
            "responseHashes": [
                "11ac81113706b510ac941212aac07817547f814c956a19744eecc65f1acd83cf"
            ],
            "type": "Fetch",
            "firstPartyCookies": {},
            "firstPartyCookiesSent": {},
            "exampleSites": [
                "notion.com",
                "www.notion.so"
            ]
        },
        {
            "rule": "transcend-cdn\\.com\\/cm\\/ef49a3f1-d8c1-47d6-88fc-50e41130631f\\/airgap\\.js",
            "cookies": 0.0001,
            "fingerprinting": 2,
            "subdomains": [],
            "apis": {
                "Navigator.prototype.doNotTrack": 2,
                "Navigator.prototype.cookieEnabled": 2,
                "Navigator.prototype.userAgent": 2,
                "window.sessionStorage": 2,
                "window.localStorage": 2,
                "Navigator.prototype.languages": 2,
                "Document.cookie getter": 2,
                "CookieStore.prototype.getAll": 1,
                "Document.cookie setter": 1,
                "Event.prototype.timeStamp": 2
            },
            "sites": 2,
            "prevalence": 0.000201,
            "cnames": [],
            "responseHashes": [
                "ae252d91eeecaca5242e605d86596d24da707e684ad5c219d2ef82023b63ffed"
            ],
            "type": "Script",
            "firstPartyCookies": {
                "timezone": {
                    "ttl": null,
                    "length": 4,
                    "prevalence": 0.00010048231511254019,
                    "uniqueness": 1
                },
                "_curator_id": {
                    "ttl": 31536002,
                    "length": 32,
                    "prevalence": 0.00010048231511254019,
                    "uniqueness": 1
                },
                "optimizelySession": {
                    "ttl": 15552003,
                    "length": 13,
                    "prevalence": 0.00010048231511254019,
                    "uniqueness": 1
                },
                "_gcl_au": {
                    "ttl": 7776004,
                    "length": 24,
                    "prevalence": 0.00010048231511254019,
                    "uniqueness": 1
                },
                "_ga_4819PJ6HEN": {
                    "ttl": 63072005,
                    "length": 45,
                    "prevalence": 0.00010048231511254019,
                    "uniqueness": 1
                },
                "_ga": {
                    "ttl": 63072012,
                    "length": 27,
                    "prevalence": 0.00010048231511254019,
                    "uniqueness": 1
                },
                "_hjTLDTest": {
                    "ttl": null,
                    "length": 16,
                    "prevalence": 0.00010048231511254019,
                    "uniqueness": 1
                },
                "_hjSessionUser_864760": {
                    "ttl": 31536006,
                    "length": 115,
                    "prevalence": 0.00010048231511254019,
                    "uniqueness": 1
                },
                "_hjSession_864760": {
                    "ttl": 1806,
                    "length": 147,
                    "prevalence": 0.00010048231511254019,
                    "uniqueness": 1
                },
                "sa-user-id": {
                    "ttl": 31536006,
                    "length": 100,
                    "prevalence": 0.00010048231511254019,
                    "uniqueness": 1
                },
                "sa-user-id-v2": {
                    "ttl": 31536006,
                    "length": 85,
                    "prevalence": 0.00010048231511254019,
                    "uniqueness": 1
                },
                "sa-user-id-v3": {
                    "ttl": 31536006,
                    "length": 136,
                    "prevalence": 0.00010048231511254019,
                    "uniqueness": 1
                },
                "_ga_0HYE8YG0M6": {
                    "ttl": 63072012,
                    "length": 45,
                    "prevalence": 0.00010048231511254019,
                    "uniqueness": 1
                },
                "_gid": {
                    "ttl": 86412,
                    "length": 26,
                    "prevalence": 0.00010048231511254019,
                    "uniqueness": 1
                },
                "_gat_UA-3062505-46": {
                    "ttl": 67,
                    "length": 1,
                    "prevalence": 0.00010048231511254019,
                    "uniqueness": 1
                },
                "_fbp": {
                    "ttl": 7776008,
                    "length": 37,
                    "prevalence": 0.00010048231511254019,
                    "uniqueness": 1
                },
                "hum_tandf_visitor": {
                    "ttl": 630720011,
                    "length": 36,
                    "prevalence": 0.00010048231511254019,
                    "uniqueness": 1
                },
                "hum_tandf_synced": {
                    "ttl": 34560011,
                    "length": 4,
                    "prevalence": 0.00010048231511254019,
                    "uniqueness": 1
                }
            },
            "firstPartyCookiesSent": {},
            "exampleSites": [
                "tandfonline.com",
                "www.taylorfrancis.com"
            ]
        },
        {
            "rule": "transcend-cdn\\.com\\/cm\\/ef49a3f1-d8c1-47d6-88fc-50e41130631f\\/ui\\.js",
            "cookies": 0,
            "fingerprinting": 1,
            "subdomains": [],
            "apis": {
                "Navigator.prototype.userAgent": 2,
                "Navigator.prototype.languages": 2
            },
            "sites": 2,
            "prevalence": 0.000201,
            "cnames": [],
            "responseHashes": [
                "09077c7a4766bfe398b218bf48ef8aa21c91c7b1fb097b062e5aae2a2936a49e"
            ],
            "type": "Script",
            "firstPartyCookies": {},
            "firstPartyCookiesSent": {},
            "exampleSites": [
                "tandfonline.com",
                "www.taylorfrancis.com"
            ]
        },
        {
            "rule": "transcend-cdn\\.com\\/cm\\/ef49a3f1-d8c1-47d6-88fc-50e41130631f\\/cm\\.css",
            "cookies": 0,
            "fingerprinting": 0,
            "subdomains": [],
            "apis": {},
            "sites": 2,
            "prevalence": 0.000201,
            "cnames": [],
            "responseHashes": [
                "7239c9031099da028df9606ab70635107271c0761be8c0439f84902340b649a0"
            ],
            "type": "Stylesheet",
            "firstPartyCookies": {},
            "firstPartyCookiesSent": {},
            "exampleSites": [
                "tandfonline.com",
                "www.taylorfrancis.com"
            ]
        },
        {
            "rule": "transcend-cdn\\.com\\/cm\\/ef49a3f1-d8c1-47d6-88fc-50e41130631f\\/translations\\/de-DE\\.json",
            "cookies": 0,
            "fingerprinting": 0,
            "subdomains": [],
            "apis": {},
            "sites": 2,
            "prevalence": 0.000201,
            "cnames": [],
            "responseHashes": [
                "9003ca424386e9cc276372ff610aba11e2767b1b9a77a4b0b8bedfe4a71226bd"
            ],
            "type": "Fetch",
            "firstPartyCookies": {},
            "firstPartyCookiesSent": {},
            "exampleSites": [
                "tandfonline.com",
                "www.taylorfrancis.com"
            ]
        }
    ],
    "categories": [
        "CDN"
    ],
    "performance": {},
    "cookies": 0.000502,
    "topInitiators": [
        {
            "domain": "first party",
            "prevalence": 0.8260869565217391
        },
        {
            "domain": "notion.com",
            "prevalence": 0.08695652173913043
        },
        {
            "domain": "vimeocdn.com",
            "prevalence": 0.043478260869565216
        },
        {
            "domain": "evbstatic.com",
            "prevalence": 0.043478260869565216
        }
    ],
    "types": {
        "Script": 12,
        "Stylesheet": 4,
        "Fetch": 6
    },
    "nameservers": [
        "ingrid.ns.cloudflare.com",
        "julian.ns.cloudflare.com"
    ]
}